Metadata-Version: 2.1
Name: supercache
Version: 2.0.0
Summary: Easy to use caching decorator for functions and methods.
Home-page: https://github.com/huntfx/supercache
Author: Peter Hunt
Author-email: peter@huntfx.uk
License: MIT
Download-URL: https://github.com/huntfx/supercache/archive/2.0.0.tar.gz
Project-URL: Documentation, https://github.com/huntfx/supercache/wiki
Project-URL: Source, https://github.com/huntfx/supercache
Project-URL: Issues, https://github.com/huntfx/supercache/issues
Keywords: cache,caching,memoise,memoize,store
Platform: UNKNOWN
Classifier: Development Status :: 4 - Beta
Classifier: Intended Audience :: Developers
Classifier: License :: OSI Approved :: MIT License
Classifier: Operating System :: Microsoft :: Windows
Classifier: Operating System :: POSIX :: Linux
Classifier: Programming Language :: Python
Classifier: Programming Language :: Python :: 2
Classifier: Programming Language :: Python :: 2.7
Classifier: Programming Language :: Python :: 3
Classifier: Programming Language :: Python :: 3.3
Classifier: Programming Language :: Python :: 3.4
Classifier: Programming Language :: Python :: 3.5
Classifier: Programming Language :: Python :: 3.6
Classifier: Programming Language :: Python :: 3.7
Classifier: Programming Language :: Python :: 3.8
Classifier: Programming Language :: Python :: 3.9
Requires-Python: >=2.7, !=3.0.*, !=3.1.*, !=3.2.*
